{
  "main": {
    "id": "2fc22e343986e8e4",
    "type": "split",
    "children": [
      {
        "id": "9b51220a3ffea940",
        "type": "tabs",
        "children": [
          {
            "id": "a8d01beadf96f8db",
            "type": "leaf",
            "state": {
              "type": "markdown",
              "state": {
                "file": "Music/和声学/和声学.md",
                "mode": "source",
                "source": false
              }
            }
          }
        ]
      }
    ],
    "direction": "vertical"
  },
  "left": {
    "id": "289622fef59cbb0b",
    "type": "split",
    "children": [
      {
        "id": "6fcd2d643855c222",
        "type": "tabs",
        "children": [
          {
            "id": "c4c8a921720ece7c",
            "type": "leaf",
            "state": {
              "type": "file-explorer",
              "state": {
                "sortOrder": "alphabetical"
              }
            }
          },
          {
            "id": "4a10cd2ef3692b35",
            "type": "leaf",
            "state": {
              "type": "search",
              "state": {
                "query": "",
                "matchingCase": false,
                "explainSearch": false,
                "collapseAll": false,
                "extraContext": false,
                "sortOrder": "alphabetical"
              }
            }
          },
          {
            "id": "d7d481962bbd1559",
            "type": "leaf",
            "state": {
              "type": "bookmarks",
              "state": {}
            }
          },
          {
            "id": "b79b0f9494d05308",
            "type": "leaf",
            "state": {
              "type": "outline",
              "state": {
                "file": "Music/和声学/和声学.md"
              }
            }
          }
        ]
      }
    ],
    "direction": "horizontal",
    "width": 300
  },
  "right": {
    "id": "8dfcd87bf909f162",
    "type": "split",
    "children": [
      {
        "id": "49ee7a07bfd442d8",
        "type": "tabs",
        "children": [
          {
            "id": "3c595f1f060f6807",
            "type": "leaf",
            "state": {
              "type": "backlink",
              "state": {
                "file": "Music/和声学/和声学.md",
                "collapseAll": false,
                "extraContext": false,
                "sortOrder": "alphabetical",
                "showSearch": false,
                "searchQuery": "",
                "backlinkCollapsed": false,
                "unlinkedCollapsed": true
              }
            }
          },
          {
            "id": "537d4c0686be80e7",
            "type": "leaf",
            "state": {
              "type": "outgoing-link",
              "state": {
                "file": "Music/和声学/和声学.md",
                "linksCollapsed": false,
                "unlinkedCollapsed": true
              }
            }
          },
          {
            "id": "d9bb370fdb3d7938",
            "type": "leaf",
            "state": {
              "type": "tag",
              "state": {
                "sortOrder": "frequency",
                "useHierarchy": true
              }
            }
          }
        ],
        "currentTab": 2
      }
    ],
    "direction": "horizontal",
    "width": 300
  },
  "left-ribbon": {
    "hiddenItems": {
      "switcher:Open quick switcher": false,
      "graph:Open graph view": false,
      "canvas:Create new canvas": false,
      "daily-notes:Open today's daily note": false,
      "templates:Insert template": false,
      "command-palette:Open command palette": false
    }
  },
  "active": "c4c8a921720ece7c",
  "lastOpenFiles": [
    "Music/和声学/和弦.md",
    "Music/基本乐理.md",
    "Develop/渲染/shader.md",
    "Develop/渲染管线.md",
    "Develop/unity脚本模板.md",
    "Develop/渲染/shader graph.md",
    "Develop/Unity脚本.md",
    "Develop/unity代码模板.md",
    "Develop/Unity编辑器开发.md",
    "Develop/c sharp.md",
    "Develop/图形学.md",
    "Develop/安卓开发.md",
    "Develop/img/实验作业/image-20220607225243456.png",
    "Develop/img/实验作业/image-20220607225146274.png",
    "Develop/渲染管线.assets/image-20240830225953308.png",
    "AI/AI绘画/ai.md",
    "设计.md",
    "游戏史/通史.md",
    "游戏史/中国游戏付费史.md",
    "游戏史",
    "未命名.canvas",
    "未命名 1.canvas",
    "Pasted image 20240430144520.png",
    "Pasted image 20240430143551.png",
    "Pasted image 20240423153415.png",
    "Pasted image 20240423153404.png",
    "Pasted image 20240422150740.png",
    "AI/前向传播.py",
    "AI/test.py",
    "AI/2层的例子.py",
    "Develop/渲染管线.assets/image-20240831181840659.png",
    "Develop/渲染管线.assets/image-20240831174309147.png",
    "Develop/渲染管线.assets",
    "Develop/图形学.assets",
    "Develop/img/图形学",
    "Develop/img/实验作业",
    "Develop/img",
    "Develop/渲染",
    "markdown/markdown.md",
    "GameDesign/RPG游戏调研.md",
    "GameDesign/二次元手游.md",
    "GameDesign/RTS的数值平衡.md",
    "GameDesign/GMT理论.md",
    "GameDesign/音游中的音符命名.md",
    "GameDesign/数值公式.md",
    "GameDesign/杀戮尖塔.md",
    "GameDesign/冬之旅.md",
    "GameDesign/点积在视觉小说中的运用.md",
    "GameDesign/未命名.canvas"
  ]
}